knowledge_graph_rag_mcp/__init__.py
knowledge_graph_rag_mcp/config.py
knowledge_graph_rag_mcp/db.py
knowledge_graph_rag_mcp/embeddings.py
knowledge_graph_rag_mcp/ingest.py
knowledge_graph_rag_mcp/retrieval.py
knowledge_graph_rag_mcp/server.py
knowledge_graph_rag_mcp/cli/__init__.py
knowledge_graph_rag_mcp/cli/main.py
knowledge_graph_rag_mcp/native/__init__.py
knowledge_graph_rag_mcp/native/bfsvtab.so
knowledge_graph_rag_mcp/tools/__init__.py
knowledge_graph_rag_mcp-0.1.2.dist-info/licenses/LICENSE
knowledge_graph_rag_mcp-0.1.2.dist-info/METADATA
knowledge_graph_rag_mcp-0.1.2.dist-info/WHEEL
knowledge_graph_rag_mcp-0.1.2.dist-info/entry_points.txt
knowledge_graph_rag_mcp-0.1.2.dist-info/top_level.txt
knowledge_graph_rag_mcp-0.1.2.dist-info/RECORD
