Metadata-Version: 2.4
Name: knowledge-graph-rag-mcp
Version: 0.1.2
Summary: Local-first Knowledge GraphRAG MCP server
Home-page: https://github.com/anthropic-ai/knowledge-graph-rag-mcp
Author: Knowledge GraphRAG Team
License: MIT
Classifier: Programming Language :: Python :: 3
Classifier: License :: OSI Approved :: MIT License
Classifier: Operating System :: OS Independent
Requires-Python: >=3.10
License-File: LICENSE
Requires-Dist: PyYAML>=6.0
Requires-Dist: typer>=0.9
Requires-Dist: sqlite-vec>=0.1.6
Requires-Dist: huggingface-hub>=0.19
Dynamic: license-file
